rlbase/__init__.py
rlbase/agent.py
rlbase/environment.py
rlbase/experiment.py
rlbase/misc.py
rlbase/policy.py
rlbase/policy_functions.py
rlbase_chicotobi-0.6.0.dist-info/LICENSE
rlbase_chicotobi-0.6.0.dist-info/METADATA
rlbase_chicotobi-0.6.0.dist-info/WHEEL
rlbase_chicotobi-0.6.0.dist-info/top_level.txt
rlbase_chicotobi-0.6.0.dist-info/RECORD
